agentsociety/.gitignore
agentsociety/DESIGN.md
agentsociety/__init__.py
agentsociety/_dist/favicon.png
agentsociety/_dist/index.html
agentsociety/_dist/logo.png
agentsociety/_dist/assets/index-BcoUTOjn.js
agentsociety/_dist/assets/index-CyMArPO0.css
agentsociety/_dist/assets/mapbox-gl-CkhHkf0q.js
agentsociety/_dist/icon/agent.png
agentsociety/_dist/icon/agent.svg
agentsociety/_dist/icon/boy1.png
agentsociety/_dist/icon/boy2.png
agentsociety/_dist/icon/boy3.png
agentsociety/_dist/icon/girl1.png
agentsociety/_dist/icon/girl2.png
agentsociety/_dist/icon/girl3.png
agentsociety/_dist/icon/history.png
agentsociety/_dist/icon/info.png
agentsociety/_dist/icon/status.png
agentsociety/_dist/monaco-editor/min/vs/loader.js
agentsociety/_dist/monaco-editor/min/vs/base/browser/ui/codicons/codicon/codicon.ttf
agentsociety/_dist/monaco-editor/min/vs/base/common/worker/simpleWorker.nls.de.js
agentsociety/_dist/monaco-editor/min/vs/base/common/worker/simpleWorker.nls.es.js
agentsociety/_dist/monaco-editor/min/vs/base/common/worker/simpleWorker.nls.fr.js
agentsociety/_dist/monaco-editor/min/vs/base/common/worker/simpleWorker.nls.it.js
agentsociety/_dist/monaco-editor/min/vs/base/common/worker/simpleWorker.nls.ja.js
agentsociety/_dist/monaco-editor/min/vs/base/common/worker/simpleWorker.nls.js
agentsociety/_dist/monaco-editor/min/vs/base/common/worker/simpleWorker.nls.ko.js
agentsociety/_dist/monaco-editor/min/vs/base/common/worker/simpleWorker.nls.ru.js
agentsociety/_dist/monaco-editor/min/vs/base/common/worker/simpleWorker.nls.zh-cn.js
agentsociety/_dist/monaco-editor/min/vs/base/common/worker/simpleWorker.nls.zh-tw.js
agentsociety/_dist/monaco-editor/min/vs/base/worker/workerMain.js
agentsociety/_dist/monaco-editor/min/vs/basic-languages/abap/abap.js
agentsociety/_dist/monaco-editor/min/vs/basic-languages/apex/apex.js
agentsociety/_dist/monaco-editor/min/vs/basic-languages/azcli/azcli.js
agentsociety/_dist/monaco-editor/min/vs/basic-languages/bat/bat.js
agentsociety-1.5.6.dist-info/METADATA
agentsociety-1.5.6.dist-info/WHEEL
agentsociety-1.5.6.dist-info/entry_points.txt
agentsociety-1.5.6.dist-info/licenses/LICENSE
agentsociety-1.5.6.dist-info/RECORD
