Metadata-Version: 2.4
Name: agentsociety
Version: 1.5.6
Summary: LLM-based city environment agent building library
Project-URL: Homepage, https://github.com/tsinghua-fib-lab/agentsociety
Project-URL: Repository, https://github.com/tsinghua-fib-lab/agentsociety.git
Project-URL: Issues, https://github.com/tsinghua-fib-lab/agentsociety/issues
Author-email: Yuwei Yan <pinkgranite86@gmail.com>, Junbo Yan <yanjb20thu@gmail.com>, Jun Zhang <zhangjun990222@gmail.com>, Zhiheng Zheng <zhengzh20@gmail.com>
License:                                  Apache License
License-File: LICENSE
Classifier: Operating System :: MacOS :: MacOS X
Classifier: Operating System :: POSIX :: Linux
Classifier: Programming Language :: Python :: 3
Requires-Python: >=3.11
Requires-Dist: aiodocker>=0.24.0
Requires-Dist: aiosqlite>=0.21.0
Requires-Dist: asyncpg>=0.30.0
Requires-Dist: boto3>=1.37
Requires-Dist: casdoor>=1.29.0
Requires-Dist: click>=8.0.0
Requires-Dist: fastapi>=0.103.1
Requires-Dist: geojson>=3.1.0
Requires-Dist: grpcio<2.0.0,>=1.71.0
Requires-Dist: json-repair>=0.46.2
Requires-Dist: kubernetes-asyncio>=32.3.0
Requires-Dist: numpy<2.0.0,>=1.20.0
Requires-Dist: openai>=1.58.1
Requires-Dist: protobuf<5.0.0,<=4.24.0
Requires-Dist: pycityproto>=2.4.2
Requires-Dist: pydantic>=2.10.4
Requires-Dist: pyproj>=3.6.0
Requires-Dist: python-dotenv>=1.0.0
Requires-Dist: python-multipart>=0.0.20
Requires-Dist: pyyaml>=6.0.2
Requires-Dist: qdrant-client[fastembed]>=1.12.1
Requires-Dist: ray[default]>=2.40.0
Requires-Dist: requests>=2.32.3
Requires-Dist: shapely>=2.0.6
Requires-Dist: sqlalchemy[asyncio]>=2.0.20
Requires-Dist: uvicorn>=0.23.2
